pytelelogger/__init__.py
pytelelogger/_threaded.py
pytelelogger/_types.py
pytelelogger/defaults.py
pytelelogger/levels.py
pytelelogger/telelogger.py
pytelelogger-0.1.1.dist-info/LICENSE
pytelelogger-0.1.1.dist-info/METADATA
pytelelogger-0.1.1.dist-info/WHEEL
pytelelogger-0.1.1.dist-info/top_level.txt
pytelelogger-0.1.1.dist-info/RECORD
