Metadata-Version: 2.1
Name: pytelelogger
Version: 0.1.1
Summary: Use Telegram bots to track your project logs in real-time.
Home-page: https://github.com/SN4KEBYTE/pytelelogger
Author: Timur Kasimov
License: GNU General Public License v3.0
Platform: UNKNOWN
Classifier: Development Status :: 4 - Beta
Classifier: Intended Audience :: Developers
Classifier: Intended Audience :: System Administrators
Classifier: License :: OSI Approved :: GNU General Public License v3 (GPLv3)
Classifier: Operating System :: Microsoft :: Windows
Classifier: Programming Language :: Python :: 3 :: Only
Classifier: Topic :: Software Development
Classifier: Typing :: Typed
Requires-Dist: python-telegram-bot (>=13.1)
Requires-Dist: pyyaml (>=5.3.1)
